{"0":{"index":"2024-09-04","Preco":769.05},"1":{"index":"2024-09-03","Preco":767.75},"2":{"index":"2024-08-21","Preco":773.2},"3":{"index":"2024-08-13","Preco":770.04},"4":{"index":"2024-08-12","Preco":770.86},"5":{"index":"2024-08-20","Preco":773.19},"6":{"index":"2024-08-19","Preco":771.23},"7":{"index":"2024-08-16","Preco":771.71},"8":{"index":"2024-08-15","Preco":771.86},"9":{"index":"2024-08-14","Preco":772.35},"10":{"index":"2024-09-02","Preco":767.88},"11":{"index":"2024-08-30","Preco":768.33},"12":{"index":"2024-08-29","Preco":770.86},"13":{"index":"2024-08-28","Preco":773.26},"14":{"index":"2024-08-27","Preco":773.73},"15":{"index":"2024-08-26","Preco":773.23},"16":{"index":"2024-08-23","Preco":771.76},"17":{"index":"2024-08-22","Preco":772.4},"18":{"index":"2024-09-06","Preco":774.99},"19":{"index":"2024-09-05","Preco":772.1}}